pytest_mypy.py
pytest_mypyd-0.3.5.dist-info/LICENSE
pytest_mypyd-0.3.5.dist-info/METADATA
pytest_mypyd-0.3.5.dist-info/WHEEL
pytest_mypyd-0.3.5.dist-info/entry_points.txt
pytest_mypyd-0.3.5.dist-info/top_level.txt
pytest_mypyd-0.3.5.dist-info/RECORD
