Metadata-Version: 2.1
Name: pytest-mypyd
Version: 0.3.5
Summary: Mypy static type checker plugin for Pytest
Home-page: https://gitlab.com/pv.zarubin/pytest-mypy
Author: Daniel Bader
Author-email: mail@dbader.org
Maintainer: David Tucker
Maintainer-email: david@tucker.name
License: MIT
Platform: UNKNOWN
Classifier: Development Status :: 4 - Beta
Classifier: Framework :: Pytest
Classifier: Intended Audience :: Developers
Classifier: Topic :: Software Development :: Testing
Classifier: Programming Language :: Python
Classifier: Programming Language :: Python :: 3
Classifier: Programming Language :: Python :: 3.4
Classifier: Programming Language :: Python :: 3.5
Classifier: Programming Language :: Python :: 3.6
Classifier: Programming Language :: Python :: 3.7
Classifier: Programming Language :: Python :: 3.8
Classifier: Programming Language :: Python :: Implementation :: CPython
Classifier: Operating System :: OS Independent
Classifier: License :: OSI Approved :: MIT License
Requires-Python: ~=3.4
Requires-Dist: pytest (<4.7,>=2.8) ; python_version < "3.5"
Requires-Dist: mypy (<0.700,>=0.570) ; python_version < "3.5"
Requires-Dist: pytest (>=2.8) ; python_version >= "3.5"
Requires-Dist: mypy (>=0.570) ; python_version >= "3.5"
Requires-Dist: mypy (>=0.701) ; python_version >= "3.8.0b1"
